evobiomat/EvoBioMat.py
evobiomat/__init__.py
evobiomat/api/__init__.py
evobiomat/api/types.py
evobiomat/biometric/__init__.py
evobiomat/biometric/engine.py
evobiomat/camera/__init__.py
evobiomat/camera/capture.py
evobiomat/database/__init__.py
evobiomat/database/client.py
evobiomat/errors/__init__.py
evobiomat/errors/exceptions.py
evobiomat/security/__init__.py
evobiomat/security/crypto.py
evobiomat-1.0.0.dist-info/licenses/LICENSE
evobiomat-1.0.0.dist-info/METADATA
evobiomat-1.0.0.dist-info/WHEEL
evobiomat-1.0.0.dist-info/top_level.txt
evobiomat-1.0.0.dist-info/RECORD
