Metadata-Version: 2.4
Name: evoBioMat
Version: 1.0.0
Summary: Enterprise-grade face biometric SDK
Home-page: https://github.com/dakshdubey/evoBioMat_SDK
Author: Daksha Dubey
Author-email: evofu1007@gmail.com
License: MIT
Classifier: Programming Language :: Python :: 3
Classifier: License :: OSI Approved :: MIT License
Classifier: Operating System :: OS Independent
Requires-Python: >=3.10
License-File: LICENSE
Requires-Dist: opencv-python
Requires-Dist: face-recognition
Requires-Dist: numpy
Requires-Dist: pymysql
Requires-Dist: cryptography
Dynamic: license-file
